<BackupInst xmlns="http://www.microsoft.com/GroupPolicy/GPOOperations/Manifest"><GPOGuid><![CDATA[{60F1C050-B980-4703-9AD6-2E8E8893BFC2}]]></GPOGuid><GPODomain><![CDATA[acme.local]]></GPODomain><GPODomainGuid><![CDATA[{7d1770e0-824e-41ef-80a7-4b6db42e7f3f}]]></GPODomainGuid><GPODomainController><![CDATA[DC01.acme.local]]></GPODomainController><BackupTime><![CDATA[2020-11-09T19:47:31]]></BackupTime><ID><![CDATA[{36B5C7F0-FA62-463F-8EFA-E904FDC95ADC}]]></ID><Comment><![CDATA[]]></Comment><GPODisplayName><![CDATA[threathuntGPO]]></GPODisplayName></BackupInst>
