<BackupInst xmlns="http://www.microsoft.com/GroupPolicy/GPOOperations/Manifest"><GPOGuid><![CDATA[{BC5FA16F-EA5F-4189-A80C-3FE9D231E4AE}]]></GPOGuid><GPODomain><![CDATA[acme.local]]></GPODomain><GPODomainGuid><![CDATA[{13fb9f31-d24d-4d72-8594-685219b20ed3}]]></GPODomainGuid><GPODomainController><![CDATA[DC01.acme.local]]></GPODomainController><BackupTime><![CDATA[2020-11-22T10:18:28]]></BackupTime><ID><![CDATA[{1FF262E6-30B2-4971-8A7F-4F289546D229}]]></ID><Comment><![CDATA[]]></Comment><GPODisplayName><![CDATA[threathuntFIREWALL]]></GPODisplayName></BackupInst>
