<BackupInst xmlns="http://www.microsoft.com/GroupPolicy/GPOOperations/Manifest"><GPOGuid><![CDATA[{D93E8752-0247-4B46-8CF4-E464F883659F}]]></GPOGuid><GPODomain><![CDATA[acme.local]]></GPODomain><GPODomainGuid><![CDATA[{65215dd5-8ea6-4ca1-b208-c6d919f01063}]]></GPODomainGuid><GPODomainController><![CDATA[DC01.acme.local]]></GPODomainController><BackupTime><![CDATA[2020-10-01T16:41:33]]></BackupTime><ID><![CDATA[{AE84C18C-323A-47C9-8483-EC5088EA1882}]]></ID><Comment><![CDATA[]]></Comment><GPODisplayName><![CDATA[threathuntUPDATE]]></GPODisplayName></BackupInst>
