<BackupInst xmlns="http://www.microsoft.com/GroupPolicy/GPOOperations/Manifest"><GPOGuid><![CDATA[{9DDE6476-D55E-4575-A8FA-E3EBD07FB1DB}]]></GPOGuid><GPODomain><![CDATA[acme.local]]></GPODomain><GPODomainGuid><![CDATA[{13fb9f31-d24d-4d72-8594-685219b20ed3}]]></GPODomainGuid><GPODomainController><![CDATA[DC01.acme.local]]></GPODomainController><BackupTime><![CDATA[2020-11-22T10:18:28]]></BackupTime><ID><![CDATA[{C64AE9CE-C601-483D-B3C3-51EC5732C3B6}]]></ID><Comment><![CDATA[]]></Comment><GPODisplayName><![CDATA[threathuntUAC]]></GPODisplayName></BackupInst>
