<BackupInst xmlns="http://www.microsoft.com/GroupPolicy/GPOOperations/Manifest"><GPOGuid><![CDATA[{7B49A8D3-619D-4631-B2B1-9CE69537AC34}]]></GPOGuid><GPODomain><![CDATA[acme.local]]></GPODomain><GPODomainGuid><![CDATA[{13fb9f31-d24d-4d72-8594-685219b20ed3}]]></GPODomainGuid><GPODomainController><![CDATA[DC01.acme.local]]></GPODomainController><BackupTime><![CDATA[2020-11-22T10:18:26]]></BackupTime><ID><![CDATA[{B1107DFB-2AD5-462B-BD3B-9BEE28582206}]]></ID><Comment><![CDATA[]]></Comment><GPODisplayName><![CDATA[threathuntDEFENDER]]></GPODisplayName></BackupInst>
